bashstylr/BashStylr.py
bashstylr/__init__.py
bashstylr-1.0.0.dist-info/METADATA
bashstylr-1.0.0.dist-info/WHEEL
bashstylr-1.0.0.dist-info/licenses/LICENSE
bashstylr-1.0.0.dist-info/RECORD
