Metadata-Version: 2.4
Name: bashstylr
Version: 1.0.0
Summary: A Python library for styling bash
Project-URL: Repository, https://github.com/sneekyfoxx/bashstylr.git
Project-URL: Issues, https://github.com/sneekyfoxx/bashstylr/issues
Author-email: Rayshawn Levy <sneekyfoxx09@gmail.com>
Maintainer-email: Rayshawn Levy <sneekyfoxx09@gmail.com>
License: MIT License
License-File: LICENSE
Keywords: bash,bashstylr,stylr
Classifier: Programming Language :: Python :: 3.12
Classifier: Programming Language :: Python :: 3.13
Requires-Python: >=3.12
